yappyg/__init__.py
yappyg/test/__init__.py
yappyg/test/test_yappyg.py
yappyg-0.1.6.dist-info/LICENSE
yappyg-0.1.6.dist-info/LICENSE-BRIGIT
yappyg-0.1.6.dist-info/METADATA
yappyg-0.1.6.dist-info/WHEEL
yappyg-0.1.6.dist-info/top_level.txt
yappyg-0.1.6.dist-info/RECORD
