Metadata-Version: 2.1
Name: yappyg
Version: 0.1.6
Summary: Yet Another Package for Py Git, that handles user/pass prompts in native python
Home-page: https://github.com/lucasdurand/yappyG
Author: Lucas Durand
Author-email: lucas@lucasdurand.xyz
License: BSD
Platform: Any
Classifier: Development Status :: 2 - Pre-Alpha
Classifier: Intended Audience :: Developers
Classifier: License :: OSI Approved :: BSD License
Classifier: Operating System :: OS Independent
Classifier: Programming Language :: Python :: 3
Classifier: Topic :: Software Development :: Libraries :: Python Modules
Provides: yappyg
Requires-Dist: log-colorizer
Requires-Dist: nbdime
